kestrel_analytics_docker/__init__.py
kestrel_analytics_docker/config.py
kestrel_analytics_docker/interface.py
kestrel_analytics_docker-1.8.1.dist-info/METADATA
kestrel_analytics_docker-1.8.1.dist-info/WHEEL
kestrel_analytics_docker-1.8.1.dist-info/top_level.txt
kestrel_analytics_docker-1.8.1.dist-info/RECORD
